{
	"format_version": "1.8.0",
	"animations": {
		"animation.model.new": {
			"animation_length": 0.75,
			"bones": {
				"legs": {
					"rotation": {
						"0.0": {
							"vector": [0, 0, 0]
						},
						"0.05": {
							"vector": [-0.51854, -5.66132, -2.79971]
						},
						"0.75": {
							"vector": [0, 0, 0]
						}
					}
				},
				"bone1": {
					"position": {
						"0.0": {
							"vector": [0, 0, 0]
						},
						"0.05": {
							"vector": [0, 0, 1]
						},
						"0.75": {
							"vector": [0, 0, 0]
						}
					}
				},
				"bone2": {
					"rotation": {
						"0.0": {
							"vector": [2.34683, 0.94351, -0.33156]
						},
						"0.25": {
							"vector": [30, 0, 0]
						},
						"0.5": {
							"vector": [-35, 0, 0]
						},
						"0.75": {
							"vector": [2.34683, 0.94351, -0.33156]
						}
					},
					"position": {
						"0.0": {
							"vector": [0, 0, 0]
						},
						"0.25": {
							"vector": [0, 1, 4]
						},
						"0.5": {
							"vector": [0, 0, 4]
						},
						"0.75": {
							"vector": [0, 0, 0]
						}
					}
				},
				"bone3": {
					"rotation": {
						"0.0": {
							"vector": [0, 0, 0]
						},
						"0.25": {
							"vector": [-35, 0, 0]
						},
						"0.5": {
							"vector": [35, 0, 0]
						},
						"0.75": {
							"vector": [0, 0, 0]
						}
					},
					"position": {
						"0.0": {
							"vector": [0, 0, 0]
						},
						"0.75": {
							"vector": [0, 0, 0]
						}
					}
				},
				"bone4": {
					"rotation": {
						"0.0": {
							"vector": [0, 0, 0]
						},
						"0.25": {
							"vector": [-37.5, 0, 0]
						},
						"0.5": {
							"vector": [42.5, 0, 0]
						},
						"0.75": {
							"vector": [0, 0, 0]
						}
					}
				},
				"bone5": {
					"rotation": {
						"0.0": {
							"vector": [0, 0, 0]
						},
						"0.25": {
							"vector": [46.25, 0, 0]
						},
						"0.5": {
							"vector": [-32.5, 0, 0]
						},
						"0.75": {
							"vector": [0, 0, 0]
						}
					}
				},
				"bone6": {
					"rotation": {
						"0.0": {
							"vector": [-27.5, 0, 0]
						},
						"0.25": {
							"vector": [-2.5, 0, 0]
						},
						"0.5": {
							"vector": [-30, 0, 0]
						},
						"0.75": {
							"vector": [-27.5, 0, 0]
						}
					}
				}
			}
		}
	}
}